emzed_optimizations/__init__.py
emzed_optimizations/sample.pyd
emzed_optimizations/version.py
emzed_optimizations-0.6.0.dist-info/DESCRIPTION.rst
emzed_optimizations-0.6.0.dist-info/METADATA
emzed_optimizations-0.6.0.dist-info/RECORD
emzed_optimizations-0.6.0.dist-info/WHEEL
emzed_optimizations-0.6.0.dist-info/metadata.json
emzed_optimizations-0.6.0.dist-info/top_level.txt
