Metadata-Version: 2.0
Name: emzed-optimizations
Version: 0.6.0
Summary: particular optimizations for speeding up emzed
Home-page: http://github.com/uweschmitt/emzed_optimizations
Author: Uwe Schmitt
Author-email: mail@uweschmitt.info
License: BSD
Platform: UNKNOWN
